trolley.py
trolley-0.1.5.dist-info/DESCRIPTION.rst
trolley-0.1.5.dist-info/entry_points.txt
trolley-0.1.5.dist-info/METADATA
trolley-0.1.5.dist-info/metadata.json
trolley-0.1.5.dist-info/RECORD
trolley-0.1.5.dist-info/top_level.txt
trolley-0.1.5.dist-info/WHEEL
