Metadata-Version: 2.0
Name: trolley
Version: 0.1.5
Summary: Trolley syncs issues between CSV, Github, and Trello.
Home-page: http://github.com/jefftriplett/trolley
Author: Jeff Triplett
Author-email: jeff.triplett@gmail.com
License: UNKNOWN
Platform: UNKNOWN
Requires-Dist: click
Requires-Dist: click-config
Requires-Dist: github3.py
Requires-Dist: trello
